fixed_width.py
fixed_width-0.1.0.dist-info/LICENSE
fixed_width-0.1.0.dist-info/WHEEL
fixed_width-0.1.0.dist-info/METADATA
fixed_width-0.1.0.dist-info/RECORD
