Metadata-Version: 2.1
Name: fixed-width
Version: 0.1.0
Summary: Working with fixed width types.
Home-page: https://github.com/supakeen/fixed-width
License: MIT
Keywords: fixed
Author: supakeen
Author-email: cmdr@supakeen.com
Classifier: License :: OSI Approved :: MIT License
Classifier: Programming Language :: Python
Classifier: Programming Language :: Python :: 2
Classifier: Programming Language :: Python :: 2.7
Classifier: Programming Language :: Python :: 3
Classifier: Programming Language :: Python :: 3.4
Classifier: Programming Language :: Python :: 3.5
Classifier: Programming Language :: Python :: 3.6
Classifier: Programming Language :: Python :: 3.7
Classifier: Programming Language :: Python :: 3.8
Classifier: Programming Language :: Python :: 3.9
Project-URL: Repository, https://github.com/supakeen/fixed-width
